{
    "hap": {
        "protocol": "http_test",
        "host": "ihap-pre.sp.vodafone.com_test"
    },
    "apix": {
        "protocol": "https_test",
        "host": "apisit.developer.vodafone.com_test",
        "oAuthTokenPath": "/2/oauth/access-token_test",
        "oAuthTokenScope": "seamless_id_resolve_test",
        "oAuthTokenGrantType": "client_credentials_test"
    },
    "basePath": "/seamless-id/users/tokens_test",
    "defaultHttpConnectionTimeout": 56,
    "requestsThrottlingLimit": 23,
    "requestsThrottlingPeriod": 45,
    "availableMarkets" : {"PT_test": 123333},
    "phoneNumberRegex": "^[0-9]{7,12}$_test",
    "availableMccMnc": ["26801_test"]
}